larpixweb/__init__.py
larpixweb/app.py
larpixweb/daq.py
larpixweb/server.py
larpixweb/build/index.447a9471076bfd3a6c447b18fb8601b3.css
larpixweb/build/index.b82336153d77532b891f.js
larpixweb/build/index.html
larpixweb/build/runtime.a9edc78d5cd6127c9851.js
larpixweb/build/static/bootstrap.min.css
larpixweb/build/static/larpix.png
larpixweb/build/static/larpixel.png
larpixweb/build/static/stylesheet.css
larpix_web-0.1.0rc2.dist-info/METADATA
larpix_web-0.1.0rc2.dist-info/WHEEL
larpix_web-0.1.0rc2.dist-info/top_level.txt
larpix_web-0.1.0rc2.dist-info/RECORD
