Metadata-Version: 2.1
Name: larpix-web
Version: 0.1.0rc2
Summary: LArPix DAQ Web Interface
Home-page: https://github.com/larpix/larpix-webapp
Author: Sam Kohn, LBNL Neutrino Group
Author-email: skohn@lbl.gov
License: UNKNOWN
Keywords: dune larpix
Platform: UNKNOWN
Classifier: Development Status :: 4 - Beta
Classifier: Intended Audience :: Science/Research
Classifier: Programming Language :: Python
Classifier: Topic :: Scientific/Engineering :: Physics
Classifier: Topic :: Scientific/Engineering
Requires-Dist: flask (>=1.0.0)
Requires-Dist: flask-socketio (>=3.0)
Requires-Dist: eventlet (>=0.24)
Requires-Dist: requests (~=2.18)
Requires-Dist: larpix-daq (~=0.2.0)
